[
    {
        "key": "dbln",
        "value": "%7B%2261573345580206%22%3A%22m6Pad0gb%22%7D",
        "domain": "facebook.com",
        "path": "/login/device-based/",
        "hostOnly": false,
        "creation": "2026-04-02T15:40:02.536Z",
        "lastAccessed": "2026-04-02T15:40:02.537Z"
    },
    {
        "key": "datr",
        "value": "ozupaYxIRSXRurVdT1jV_CGW",
        "domain": "facebook.com",
        "path": "/",
        "hostOnly": false,
        "creation": "2026-04-02T15:40:02.537Z",
        "lastAccessed": "2026-04-02T15:40:02.537Z"
    },
    {
        "key": "sb",
        "value": "uzupaXUrNsTJ7dO-992nqZT3",
        "domain": "facebook.com",
        "path": "/",
        "hostOnly": false,
        "creation": "2026-04-02T15:40:02.537Z",
        "lastAccessed": "2026-04-02T15:40:02.537Z"
    },
    {
        "key": "ps_l",
        "value": "1",
        "domain": "facebook.com",
        "path": "/",
        "hostOnly": false,
        "creation": "2026-04-02T15:40:02.537Z",
        "lastAccessed": "2026-04-02T15:40:02.537Z"
    },
    {
        "key": "ps_n",
        "value": "1",
        "domain": "facebook.com",
        "path": "/",
        "hostOnly": false,
        "creation": "2026-04-02T15:40:02.537Z",
        "lastAccessed": "2026-04-02T15:40:02.537Z"
    },
    {
        "key": "locale",
        "value": "en_US",
        "domain": "facebook.com",
        "path": "/",
        "hostOnly": false,
        "creation": "2026-04-02T15:40:02.537Z",
        "lastAccessed": "2026-04-02T15:40:02.537Z"
    },
    {
        "key": "pas",
        "value": "61587897090431%3AdGm9U82OCr%2C61573345580206%3ALNSGn10COn",
        "domain": "facebook.com",
        "path": "/",
        "hostOnly": false,
        "creation": "2026-04-02T15:40:02.537Z",
        "lastAccessed": "2026-04-02T15:40:02.537Z"
    },
    {
        "key": "vpd",
        "value": "v1%3B624x360x2",
        "domain": "facebook.com",
        "path": "/",
        "hostOnly": false,
        "creation": "2026-04-02T15:40:02.537Z",
        "lastAccessed": "2026-04-02T15:40:02.537Z"
    },
    {
        "key": "m_pixel_ratio",
        "value": "2",
        "domain": "facebook.com",
        "path": "/",
        "hostOnly": false,
        "creation": "2026-04-02T15:40:02.537Z",
        "lastAccessed": "2026-04-02T15:40:02.537Z"
    },
    {
        "key": "wd",
        "value": "360x800",
        "domain": "facebook.com",
        "path": "/",
        "hostOnly": false,
        "creation": "2026-04-02T15:40:02.537Z",
        "lastAccessed": "2026-04-02T15:40:02.537Z"
    },
    {
        "key": "c_user",
        "value": "61573345580206",
        "domain": "facebook.com",
        "path": "/",
        "hostOnly": false,
        "creation": "2026-04-02T15:40:02.537Z",
        "lastAccessed": "2026-04-02T15:40:02.538Z"
    },
    {
        "key": "xs",
        "value": "31%3AJx4qk2SRq4pRbg%3A2%3A1775144313%3A-1%3A-1",
        "domain": "facebook.com",
        "path": "/",
        "hostOnly": false,
        "creation": "2026-04-02T15:40:02.538Z",
        "lastAccessed": "2026-04-02T15:40:02.538Z"
    },
    {
        "key": "fr",
        "value": "1m0f9lSnlK3hlxT0l.AWd1MxhgXjVw3WGQ8Q54iB8rHOgaTbJk7wQ0RG4CMq80ryTmbbs.BpqTvM..AAA.0.0.Bpzo2A.AWdhZPP23RILb5Xs1z0lyjxpjtY",
        "domain": "facebook.com",
        "path": "/",
        "hostOnly": false,
        "creation": "2026-04-02T15:40:02.538Z",
        "lastAccessed": "2026-04-02T15:40:02.538Z"
    },
    {
        "key": "wl_cbv",
        "value": "v2%3Bclient_version%3A3131%3Btimestamp%3A1775144320",
        "domain": "facebook.com",
        "path": "/",
        "hostOnly": false,
        "creation": "2026-04-02T15:40:02.538Z",
        "lastAccessed": "2026-04-02T15:40:02.538Z"
    },
    {
        "key": "fbl_st",
        "value": "100432420%3BT%3A29585738",
        "domain": "facebook.com",
        "path": "/",
        "hostOnly": false,
        "creation": "2026-04-02T15:40:02.538Z",
        "lastAccessed": "2026-04-02T15:40:02.538Z"
    }
]
