[
    {
        "key": "dbln",
        "value": "%7B%2261588329035629%22%3A%22Pyw47MJe%22%7D",
        "domain": "facebook.com",
        "path": "/login/device-based/",
        "hostOnly": false,
        "creation": "2026-03-03T16:10:05.078Z",
        "lastAccessed": "2026-03-03T16:10:05.080Z"
    },
    {
        "key": "datr",
        "value": "OaGIaRGuFv9r3Gy6gH1d7_ba",
        "domain": "facebook.com",
        "path": "/",
        "hostOnly": false,
        "creation": "2026-03-03T16:10:05.080Z",
        "lastAccessed": "2026-03-03T16:10:05.080Z"
    },
    {
        "key": "sb",
        "value": "OqGIaVKIugTmOZjTqHQhPWuY",
        "domain": "facebook.com",
        "path": "/",
        "hostOnly": false,
        "creation": "2026-03-03T16:10:05.080Z",
        "lastAccessed": "2026-03-03T16:10:05.080Z"
    },
    {
        "key": "ps_l",
        "value": "1",
        "domain": "facebook.com",
        "path": "/",
        "hostOnly": false,
        "creation": "2026-03-03T16:10:05.080Z",
        "lastAccessed": "2026-03-03T16:10:05.080Z"
    },
    {
        "key": "ps_n",
        "value": "1",
        "domain": "facebook.com",
        "path": "/",
        "hostOnly": false,
        "creation": "2026-03-03T16:10:05.080Z",
        "lastAccessed": "2026-03-03T16:10:05.080Z"
    },
    {
        "key": "pas",
        "value": "61586630116459%3A5s7DNYByEG%2C61587432553080%3AnPdObw8Rk1%2C61587897090431%3Aa0WuXIZdX2%2C61588329035629%3AsjI8BpbJuo",
        "domain": "facebook.com",
        "path": "/",
        "hostOnly": false,
        "creation": "2026-03-03T16:10:05.080Z",
        "lastAccessed": "2026-03-03T16:10:05.080Z"
    },
    {
        "key": "locale",
        "value": "en_US",
        "domain": "facebook.com",
        "path": "/",
        "hostOnly": false,
        "creation": "2026-03-03T16:10:05.080Z",
        "lastAccessed": "2026-03-03T16:10:05.080Z"
    },
    {
        "key": "m_pixel_ratio",
        "value": "2",
        "domain": "facebook.com",
        "path": "/",
        "hostOnly": false,
        "creation": "2026-03-03T16:10:05.080Z",
        "lastAccessed": "2026-03-03T16:10:05.080Z"
    },
    {
        "key": "wd",
        "value": "360x800",
        "domain": "facebook.com",
        "path": "/",
        "hostOnly": false,
        "creation": "2026-03-03T16:10:05.080Z",
        "lastAccessed": "2026-03-03T16:10:05.080Z"
    },
    {
        "key": "c_user",
        "value": "61587897090431",
        "domain": "facebook.com",
        "path": "/",
        "hostOnly": false,
        "creation": "2026-03-03T16:10:05.080Z",
        "lastAccessed": "2026-03-03T16:10:05.080Z"
    },
    {
        "key": "xs",
        "value": "1%3AKojY7ZMP7jLhXQ%3A2%3A1772553706%3A-1%3A-1",
        "domain": "facebook.com",
        "path": "/",
        "hostOnly": false,
        "creation": "2026-03-03T16:10:05.080Z",
        "lastAccessed": "2026-03-03T16:10:05.080Z"
    },
    {
        "key": "ar_debug",
        "value": "1",
        "domain": "facebook.com",
        "path": "/",
        "hostOnly": false,
        "creation": "2026-03-03T16:10:05.081Z",
        "lastAccessed": "2026-03-03T16:10:05.081Z"
    },
    {
        "key": "fr",
        "value": "0E6oolXqq8ZiEiPZD.AWfhCNa83J648nmIG6RrbPQ7W6Eouf3TmAOHhiKvQjt0sbp-FXM.BpiKE6..AAA.0.0.Bppwd0.AWc2BT_KPM30ARqqaNdZ2YnJwYU",
        "domain": "facebook.com",
        "path": "/",
        "hostOnly": false,
        "creation": "2026-03-03T16:10:05.081Z",
        "lastAccessed": "2026-03-03T16:10:05.081Z"
    },
    {
        "key": "fbl_st",
        "value": "101722308%3BT%3A29542568",
        "domain": "facebook.com",
        "path": "/",
        "hostOnly": false,
        "creation": "2026-03-03T16:10:05.081Z",
        "lastAccessed": "2026-03-03T16:10:05.081Z"
    },
    {
        "key": "wl_cbv",
        "value": "v2%3Bclient_version%3A3102%3Btimestamp%3A1772554100",
        "domain": "facebook.com",
        "path": "/",
        "hostOnly": false,
        "creation": "2026-03-03T16:10:05.081Z",
        "lastAccessed": "2026-03-03T16:10:05.081Z"
    },
    {
        "key": "vpd",
        "value": "v1%3B624x360x2",
        "domain": "facebook.com",
        "path": "/",
        "hostOnly": false,
        "creation": "2026-03-03T16:10:05.081Z",
        "lastAccessed": "2026-03-03T16:10:05.081Z"
    }
]
